wirinj/__init__.py
wirinj/autowiring.py
wirinj/core.py
wirinj/decorators.py
wirinj/definition.py
wirinj/dependencies.py
wirinj/errors.py
wirinj/injector.py
wirinj/introspect.py
wirinj/locators.py
wirinj/tools.py
wirinj-0.7.8.dist-info/LICENSE
wirinj-0.7.8.dist-info/METADATA
wirinj-0.7.8.dist-info/WHEEL
wirinj-0.7.8.dist-info/top_level.txt
wirinj-0.7.8.dist-info/RECORD
