Metadata-Version: 2.1
Name: wirinj
Version: 0.7.8
Summary: A comfy dependency injection library.
Home-page: https://github.com/davidcim/wirinj
Author: David Cimadevilla
Author-email: dev.davidcim@gmail.com
License: UNKNOWN
Platform: UNKNOWN
Classifier: Programming Language :: Python :: 3
Classifier: License :: OSI Approved :: MIT License
Classifier: Operating System :: OS Independent
Requires-Python: >=3.6
